quark_plugin_dwave/__init__.py
quark_plugin_dwave/mis_qubo_mapping_dnx.py
quark_plugin_dwave/simulated_annealer_dwave.py
quark_plugin_dwave/tsp_qubo_mapping_dnx.py
quark_plugin_dwave-0.3.0.dist-info/licenses/LICENSE
quark_plugin_dwave-0.3.0.dist-info/licenses/NOTICE
quark_plugin_dwave-0.3.0.dist-info/METADATA
quark_plugin_dwave-0.3.0.dist-info/WHEEL
quark_plugin_dwave-0.3.0.dist-info/top_level.txt
quark_plugin_dwave-0.3.0.dist-info/RECORD
