Metadata-Version: 2.4
Name: QUARK-plugin-dwave
Version: 0.3.0
Author-email: Philipp Ross <philipp.ross@bmw.de>, Marvin Erdmann <marvin.erdmann@bmw.de>, Andre Luckow <andre.luckow@bmwgroup.com>, Greshma Shaji <greshma.shaji@bmwgroup.com>, Florian Kiwit <florian.kiwit@bmw.de>, Benjamin Decker <benjamin.decker@bmw.de>
License-Expression: Apache-2.0
Project-URL: Homepage, https://github.com/QUARK-framework/QUARK-plugin-dwave
Classifier: Programming Language :: Python :: 3
Classifier: Operating System :: OS Independent
Requires-Python: >=3.12
License-File: LICENSE
License-File: NOTICE
Requires-Dist: dwave-networkx>=0.8.18
Requires-Dist: dwave-samplers>=1.6.0
Requires-Dist: quark-framework>=0.4.1
Requires-Dist: quark-plugin-tsp>=2.3.0
Dynamic: license-file
